SerShulyak53501/constans.py
SerShulyak53501/fabric_ser.py
SerShulyak53501/json_ser.py
SerShulyak53501/sezializer.py
SerShulyak53501/xml_ser.py
SerShulyak53501-0.1.0.dist-info/METADATA
SerShulyak53501-0.1.0.dist-info/WHEEL
SerShulyak53501-0.1.0.dist-info/top_level.txt
SerShulyak53501-0.1.0.dist-info/RECORD
